{
  "name": "MT_multiplicacao",
  "blank": "_",
  "initial_state": "q1",
  "final_states": ["q7"],
  "transitions": [
    { "state": "q1", "read": "1", "next_state": "q2", "write": "X", "move": "R" },
    { "state": "q1", "read": "$", "next_state": "q7", "write": "$", "move": "R" },

    { "state": "q2", "read": "1", "next_state": "q2", "write": "1", "move": "R" },
    { "state": "q2", "read": "$", "next_state": "q3", "write": "$", "move": "R" },

    { "state": "q3", "read": "1", "next_state": "q4", "write": "Y", "move": "R" },
    { "state": "q3", "read": "@", "next_state": "q6", "write": "@", "move": "L" },

    { "state": "q4", "read": "1", "next_state": "q4", "write": "1", "move": "R" },
    { "state": "q4", "read": "@", "next_state": "q4", "write": "@", "move": "R" },
    { "state": "q4", "read": "_", "next_state": "q5", "write": "1", "move": "L" },

    { "state": "q5", "read": "@", "next_state": "q5", "write": "@", "move": "L" },
    { "state": "q5", "read": "1", "next_state": "q5", "write": "1", "move": "L" },
    { "state": "q5", "read": "Y", "next_state": "q3", "write": "Y", "move": "R" },

    { "state": "q6", "read": "Y", "next_state": "q6", "write": "1", "move": "L" },
    { "state": "q6", "read": "$", "next_state": "q6", "write": "$", "move": "L" },
    { "state": "q6", "read": "1", "next_state": "q6", "write": "1", "move": "L" },
    { "state": "q6", "read": "X", "next_state": "q1", "write": "X", "move": "R" }
  ]
}
